{ "skeleton": { "images": "C:/Users/은영/Downloads/알토이게임즈_다함께 쿠킹팡/알토이게임즈_다함께 쿠킹팡/1.캐릭터&몬스터/ch17/psd/images/" },
"bones": [
	{ "name": "root" }
],
"slots": [
	{ "name": "왼발", "bone": "root", "attachment": "왼발" },
	{ "name": "오른발", "bone": "root", "attachment": "오른발" },
	{ "name": "오른팔", "bone": "root", "attachment": "오른팔" },
	{ "name": "몸통", "bone": "root", "attachment": "몸통" },
	{ "name": "왼팔", "bone": "root", "attachment": "왼팔" }
],
"skins": {
	"default": {
		"왼발": {
			"왼발": { "x": 294, "y": -743, "width": 78, "height": 160 }
		},
		"오른발": {
			"오른발": { "x": 482, "y": -743, "width": 78, "height": 160 }
		},
		"오른팔": {
			"오른팔": { "x": 615, "y": -536.5, "width": 166, "height": 205 }
		},
		"몸통": {
			"몸통": { "x": 390.5, "y": -363, "width": 765, "height": 728 }
		},
		"왼팔": {
			"왼팔": { "x": 82, "y": -536.5, "width": 166, "height": 205 }
		}
	}
},
"animations": { "animation": {} }
}